pautomount.py
pautomount-1.0.0.dist-info/DESCRIPTION.rst
pautomount-1.0.0.dist-info/METADATA
pautomount-1.0.0.dist-info/RECORD
pautomount-1.0.0.dist-info/WHEEL
pautomount-1.0.0.dist-info/entry_points.txt
pautomount-1.0.0.dist-info/metadata.json
pautomount-1.0.0.dist-info/top_level.txt
