Metadata-Version: 2.0
Name: pautomount
Version: 1.0.0
Summary: A daemon for automounting and/or executing actions on hotplug of removable drives
Home-page: https://github.com/CRImier/pautomount
Author: Arsenijs Picugins
Author-email: crimier@yandex.ru
License: UNKNOWN
Download-URL: https://github.com/CRImier/pautomount/archive/1.0.0.tar.gz
Keywords: linux,partitions,automount,usb,flash drives
Platform: UNKNOWN
Requires-Dist: pyrtitions (>=0.2.2)
